tdse/__init__.py
tdse/analytic.py
tdse/coordinate.py
tdse/grid.py
tdse/hamiltonian.py
tdse/matrix.py
tdse/ntype.py
tdse/potential.py
tdse/state.py
tdse/system.py
tdse/version.py
tdse-0.0.2.dist-info/DESCRIPTION.rst
tdse-0.0.2.dist-info/METADATA
tdse-0.0.2.dist-info/RECORD
tdse-0.0.2.dist-info/WHEEL
tdse-0.0.2.dist-info/metadata.json
tdse-0.0.2.dist-info/top_level.txt
