Metadata-Version: 2.0
Name: tdse
Version: 0.0.2
Summary: Simple TDSE simulator
Home-page: UNKNOWN
Author: sahn
Author-email: jam31118@gmail.com
License: GPLv3
Keywords: physics,quantum mechanics,simulation
Platform: UNKNOWN
Classifier: Topic :: Scientific/Engineering :: Physics
Classifier: License :: OSI Approved :: GNU Affero General Public License v3
Classifier: Programming Language :: Python :: 3.5
Classifier: Programming Language :: Python :: 3.6
Requires-Dist: numpy
Requires-Dist: matplotlib
Requires-Dist: vis
Requires-Dist: nunit
Requires-Dist: ntype
